{
  "indexes": [
    {
      "collectionGroup": "taxi_requests",
      "queryScope": "COLLECTION",
      "fields": [
        {
          "fieldPath": "status",
          "order": "ASCENDING"
        },
        {
          "fieldPath": "broadcastSentTo",
          "arrayConfig": "CONTAINS"
        },
        {
          "fieldPath": "createdAt",
          "order": "DESCENDING"
        }
      ]
    },
    {
      "collectionGroup": "taxi_requests",
      "queryScope": "COLLECTION",
      "fields": [
        {
          "fieldPath": "status",
          "order": "ASCENDING"
        },
        {
          "fieldPath": "createdAt",
          "order": "DESCENDING"
        }
      ]
    },
    {
      "collectionGroup": "bookings",
      "queryScope": "COLLECTION",
      "fields": [
        {
          "fieldPath": "userId",
          "order": "ASCENDING"
        },
        {
          "fieldPath": "date",
          "order": "DESCENDING"
        }
      ]
    },
    {
      "collectionGroup": "connectCuration",
      "queryScope": "COLLECTION",
      "fields": [
        {
          "fieldPath": "section",
          "order": "ASCENDING"
        },
        {
          "fieldPath": "isActive",
          "order": "ASCENDING"
        },
        {
          "fieldPath": "order",
          "order": "ASCENDING"
        }
      ]
    },
    {
      "collectionGroup": "connectCuration",
      "queryScope": "COLLECTION",
      "fields": [
        {
          "fieldPath": "section",
          "order": "ASCENDING"
        },
        {
          "fieldPath": "region",
          "order": "ASCENDING"
        },
        {
          "fieldPath": "isActive",
          "order": "ASCENDING"
        },
        {
          "fieldPath": "order",
          "order": "ASCENDING"
        }
      ]
    },
    {
      "collectionGroup": "events",
      "queryScope": "COLLECTION",
      "fields": [
        {
          "fieldPath": "status",
          "order": "ASCENDING"
        },
        {
          "fieldPath": "startTime",
          "order": "ASCENDING"
        }
      ]
    },
    {
      "collectionGroup": "events",
      "queryScope": "COLLECTION",
      "fields": [
        {
          "fieldPath": "region",
          "order": "ASCENDING"
        },
        {
          "fieldPath": "status",
          "order": "ASCENDING"
        },
        {
          "fieldPath": "startTime",
          "order": "ASCENDING"
        }
      ]
    },
    {
      "collectionGroup": "events",
      "queryScope": "COLLECTION",
      "fields": [
        {
          "fieldPath": "businessId",
          "order": "ASCENDING"
        },
        {
          "fieldPath": "createdAt",
          "order": "DESCENDING"
        }
      ]
    },
    {
      "collectionGroup": "business_chat_sessions",
      "queryScope": "COLLECTION",
      "fields": [
        {
          "fieldPath": "businessId",
          "order": "ASCENDING"
        },
        {
          "fieldPath": "lastMessageTime",
          "order": "DESCENDING"
        }
      ]
    },
    {
      "collectionGroup": "business_bookings",
      "queryScope": "COLLECTION",
      "fields": [
        {
          "fieldPath": "businessId",
          "order": "ASCENDING"
        },
        {
          "fieldPath": "createdAt",
          "order": "DESCENDING"
        }
      ]
    },
    {
      "collectionGroup": "business_enquiries",
      "queryScope": "COLLECTION",
      "fields": [
        {
          "fieldPath": "businessId",
          "order": "ASCENDING"
        },
        {
          "fieldPath": "createdAt",
          "order": "DESCENDING"
        }
      ]
    },
    {
      "collectionGroup": "business_products",
      "queryScope": "COLLECTION",
      "fields": [
        {
          "fieldPath": "businessId",
          "order": "ASCENDING"
        },
        {
          "fieldPath": "category",
          "order": "ASCENDING"
        },
        {
          "fieldPath": "createdAt",
          "order": "DESCENDING"
        }
      ]
    },
    {
      "collectionGroup": "business_products",
      "queryScope": "COLLECTION",
      "fields": [
        {
          "fieldPath": "businessId",
          "order": "ASCENDING"
        },
        {
          "fieldPath": "available",
          "order": "ASCENDING"
        }
      ]
    },
    {
      "collectionGroup": "business_knowledge",
      "queryScope": "COLLECTION",
      "fields": [
        {
          "fieldPath": "businessId",
          "order": "ASCENDING"
        },
        {
          "fieldPath": "createdAt",
          "order": "DESCENDING"
        }
      ]
    },
    {
      "collectionGroup": "chunks",
      "queryScope": "COLLECTION_GROUP",
      "fields": [
        {
          "fieldPath": "businessId",
          "order": "ASCENDING"
        },
        {
          "fieldPath": "status",
          "order": "ASCENDING"
        },
        {
          "fieldPath": "embedding",
          "vectorConfig": {
            "dimension": 768,
            "flat": {}
          }
        }
      ]
    },
    {
      "collectionGroup": "resourceLocks",
      "queryScope": "COLLECTION_GROUP",
      "fields": [
        {
          "fieldPath": "status",
          "order": "ASCENDING"
        },
        {
          "fieldPath": "expiresAt",
          "order": "ASCENDING"
        }
      ]
    }
  ],
  "fieldOverrides": []
}